tiktok_downloader/Except.py
tiktok_downloader/__init__.py
tiktok_downloader/__main__.py
tiktok_downloader/mdown.py
tiktok_downloader/scrapper.py
tiktok_downloader/server.py
tiktok_downloader/snaptik.py
tiktok_downloader/ssstik.py
tiktok_downloader/test.py
tiktok_downloader/tikmate.py
tiktok_downloader/utils.py
tiktok_downloader-0.2.4.dist-info/METADATA
tiktok_downloader-0.2.4.dist-info/WHEEL
tiktok_downloader-0.2.4.dist-info/top_level.txt
tiktok_downloader-0.2.4.dist-info/RECORD
