Metadata-Version: 2.1
Name: tiktok-downloader
Version: 0.2.4
Summary: Tiktok Downloader&Scraper using bs4&requests
Home-page: https://github.com/krypton-byte/tiktok_downloader
Author: Krypton Byte
Author-email: galaxyvplus6434@gmail.com
License: MIT
Download-URL: https://codeload.github.com/krypton-byte/tiktok-downloader/tar.gz/refs/tags/0.2.4
Keywords: tiktok,downloader,scrapper,tikdok-scraper,tiktok-downloader
Platform: UNKNOWN
Classifier: Development Status :: 3 - Alpha
Classifier: Intended Audience :: Developers
Classifier: Topic :: Software Development :: Build Tools
Classifier: License :: OSI Approved :: MIT License
Classifier: Programming Language :: Python :: 3.8
Classifier: Programming Language :: Python :: 3.9
Requires-Dist: bs4
Requires-Dist: flask
Requires-Dist: cloudscraper
Requires-Dist: requests
Requires-Dist: py-mini-racer
